snakedream/__init__.py
snakedream/__main__.py
snakedream/base.py
snakedream/config.py
snakedream/constants.py
snakedream/device.py
snakedream/graph.py
snakedream/models.py
snakedream/mouse/__init__.py
snakedream/mouse/base.py
snakedream/mouse/device.py
snakedream/mouse/gui.py
snakedream-1.2.2.dist-info/licenses/LICENSE
snakedream-1.2.2.dist-info/METADATA
snakedream-1.2.2.dist-info/WHEEL
snakedream-1.2.2.dist-info/entry_points.txt
snakedream-1.2.2.dist-info/top_level.txt
snakedream-1.2.2.dist-info/RECORD
