Metadata-Version: 2.4
Name: snakedream
Version: 1.2.2
Summary: Python interface for a Daydream controller.
Author: Zack Didcott
Maintainer: Zack Didcott
License-Expression: MIT
Project-URL: Homepage, https://github.com/Zedeldi/snakedream
Project-URL: Repository, https://github.com/Zedeldi/snakedream.git
Project-URL: Issues, https://github.com/Zedeldi/snakedream/issues
Keywords: daydream,controller,bluetooth,uinput,bleak
Classifier: Programming Language :: Python :: 3
Classifier: Operating System :: OS Independent
Requires-Python: >=3.12
License-File: LICENSE
Requires-Dist: bleak
Requires-Dist: matplotlib
Requires-Dist: python-uinput
Requires-Dist: PyAutoGUI
Dynamic: license-file
